[{"source": {"type": "file", "filename": "30.jpg", "content_type": "image/jpeg", "md5sum": "9341e8029e681f9ddf110ebd85ebedfa"}, "results": {"predictions": [{"file": "30.jpg", "file_type": "image", "models": {"face": {"metadata": null, "grouped_predictions": [{"id": "unknown", "predictions": [{"frame": 0, "time": 0.0, "prob": 0.9999986886978149, "box": {"x": 192.6298065185547, "y": -124.26571655273438, "w": 319.36192321777344, "h": 427.71771240234375}, "emotions": [{"name": "Admiration", "score": 0.1379757672548294}, {"name": "Adoration", "score": 0.11637561023235321}, {"name": "Aesthetic Appreciation", "score": 0.07870479673147202}, {"name": "Amusement", "score": 0.3012525141239166}, {"name": "Anger", "score": 0.06290813535451889}, {"name": "Anxiety", "score": 0.14075519144535065}, {"name": "Awe", "score": 0.12550674378871918}, {"name": "Awkwardness", "score": 0.23068369925022125}, {"name": "Boredom", "score": 0.2805672287940979}, {"name": "Calmness", "score": 0.38589125871658325}, {"name": "Concentration", "score": 0.3764455020427704}, {"name": "Confusion", "score": 0.3786780536174774}, {"name": "Contemplation", "score": 0.1598026305437088}, {"name": "Contempt", "score": 0.12557648122310638}, {"name": "Contentment", "score": 0.1741446554660797}, {"name": "Craving", "score": 0.052019745111465454}, {"name": "Desire", "score": 0.07034286856651306}, {"name": "Determination", "score": 0.10119950771331787}, {"name": "Disappointment", "score": 0.2096250355243683}, {"name": "Disgust", "score": 0.08094902336597443}, {"name": "Distress", "score": 0.168480783700943}, {"name": "Doubt", "score": 0.25928211212158203}, {"name": "Ecstasy", "score": 0.0622858852148056}, {"name": "Embarrassment", "score": 0.10681532323360443}, {"name": "Empathic Pain", "score": 0.07290662825107574}, {"name": "Entrancement", "score": 0.1329723596572876}, {"name": "Envy", "score": 0.04152548313140869}, {"name": "Excitement", "score": 0.16662044823169708}, {"name": "Fear", "score": 0.0973619595170021}, {"name": "Guilt", "score": 0.06730381399393082}, {"name": "Horror", "score": 0.05499758943915367}, {"name": "Interest", "score": 0.40973004698753357}, {"name": "Joy", "score": 0.25833097100257874}, {"name": "Love", "score": 0.17341235280036926}, {"name": "Nostalgia", "score": 0.06343649327754974}, {"name": "Pain", "score": 0.09845293313264847}, {"name": "Pride", "score": 0.07404900342226028}, {"name": "Realization", "score": 0.16829735040664673}, {"name": "Relief", "score": 0.09496957808732986}, {"name": "Romance", "score": 0.06255079805850983}, {"name": "Sadness", "score": 0.14279301464557648}, {"name": "Satisfaction", "score": 0.18060444295406342}, {"name": "Shame", "score": 0.06311933696269989}, {"name": "Surprise (negative)", "score": 0.08119477331638336}, {"name": "Surprise (positive)", "score": 0.09255500882863998}, {"name": "Sympathy", "score": 0.07305311411619186}, {"name": "Tiredness", "score": 0.18643727898597717}, {"name": "Triumph", "score": 0.04519607871770859}], "facs": null, "descriptions": null}]}]}}}], "errors": []}}, {"source": {"type": "file", "filename": "100.jpg", "content_type": "image/jpeg", "md5sum": "314e88837f43ad6b3b84c3493efb3438"}, "results": {"predictions": [{"file": "100.jpg", "file_type": "image", "models": {"face": {"metadata": null, "grouped_predictions": [{"id": "unknown", "predictions": [{"frame": 0, "time": 0.0, "prob": 0.9999951124191284, "box": {"x": 207.61618041992188, "y": -62.860740661621094, "w": 266.73480224609375, "h": 386.43575286865234}, "emotions": [{"name": "Admiration", "score": 0.16121748089790344}, {"name": "Adoration", "score": 0.08514294028282166}, {"name": "Aesthetic Appreciation", "score": 0.09009374678134918}, {"name": "Amusement", "score": 0.13968786597251892}, {"name": "Anger", "score": 0.0476309210062027}, {"name": "Anxiety", "score": 0.1382477879524231}, {"name": "Awe", "score": 0.345691978931427}, {"name": "Awkwardness", "score": 0.18687760829925537}, {"name": "Boredom", "score": 0.2918684482574463}, {"name": "Calmness", "score": 0.348293274641037}, {"name": "Concentration", "score": 0.5070960521697998}, {"name": "Confusion", "score": 0.5193451642990112}, {"name": "Contemplation", "score": 0.262566477060318}, {"name": "Contempt", "score": 0.11754964292049408}, {"name": "Contentment", "score": 0.08877665549516678}, {"name": "Craving", "score": 0.07660374790430069}, {"name": "Desire", "score": 0.07402461767196655}, {"name": "Determination", "score": 0.1310432255268097}, {"name": "Disappointment", "score": 0.19089427590370178}, {"name": "Disgust", "score": 0.0451405830681324}, {"name": "Distress", "score": 0.13605016469955444}, {"name": "Doubt", "score": 0.3693336844444275}, {"name": "Ecstasy", "score": 0.0382998064160347}, {"name": "Embarrassment", "score": 0.07845412194728851}, {"name": "Empathic Pain", "score": 0.0480429045855999}, {"name": "Entrancement", "score": 0.20874999463558197}, {"name": "Envy", "score": 0.047831594944000244}, {"name": "Excitement", "score": 0.0951877012848854}, {"name": "Fear", "score": 0.1357148140668869}, {"name": "Guilt", "score": 0.05610028654336929}, {"name": "Horror", "score": 0.08251015096902847}, {"name": "Interest", "score": 0.4133569598197937}, {"name": "Joy", "score": 0.06524182111024857}, {"name": "Love", "score": 0.06912755966186523}, {"name": "Nostalgia", "score": 0.061860308051109314}, {"name": "Pain", "score": 0.044719938188791275}, {"name": "Pride", "score": 0.05421477556228638}, {"name": "Realization", "score": 0.29817235469818115}, {"name": "Relief", "score": 0.08479149639606476}, {"name": "Romance", "score": 0.04452988877892494}, {"name": "Sadness", "score": 0.08326175808906555}, {"name": "Satisfaction", "score": 0.0919145941734314}, {"name": "Shame", "score": 0.04106489568948746}, {"name": "Surprise (negative)", "score": 0.1541147530078888}, {"name": "Surprise (positive)", "score": 0.19954712688922882}, {"name": "Sympathy", "score": 0.050830624997615814}, {"name": "Tiredness", "score": 0.17846085131168365}, {"name": "Triumph", "score": 0.03292584419250488}], "facs": null, "descriptions": null}]}]}}}], "errors": []}}, {"source": {"type": "file", "filename": "20.jpg", "content_type": "image/jpeg", "md5sum": "21575fe153b1c93f56ef8338517f52bc"}, "results": {"predictions": [{"file": "20.jpg", "file_type": "image", "models": {"face": {"metadata": null, "grouped_predictions": [{"id": "unknown", "predictions": [{"frame": 0, "time": 0.0, "prob": 0.9999963045120239, "box": {"x": 221.69863891601562, "y": -114.59562683105469, "w": 315.1310119628906, "h": 426.1603546142578}, "emotions": [{"name": "Admiration", "score": 0.06978711485862732}, {"name": "Adoration", "score": 0.07274800539016724}, {"name": "Aesthetic Appreciation", "score": 0.05306922271847725}, {"name": "Amusement", "score": 0.15114086866378784}, {"name": "Anger", "score": 0.04499659314751625}, {"name": "Anxiety", "score": 0.16298158466815948}, {"name": "Awe", "score": 0.07945498079061508}, {"name": "Awkwardness", "score": 0.17146514356136322}, {"name": "Boredom", "score": 0.33949610590934753}, {"name": "Calmness", "score": 0.4139546751976013}, {"name": "Concentration", "score": 0.2807786166667938}, {"name": "Confusion", "score": 0.24223940074443817}, {"name": "Contemplation", "score": 0.14408622682094574}, {"name": "Contempt", "score": 0.09594570845365524}, {"name": "Contentment", "score": 0.14799147844314575}, {"name": "Craving", "score": 0.04963822662830353}, {"name": "Desire", "score": 0.10852831602096558}, {"name": "Determination", "score": 0.06906308978796005}, {"name": "Disappointment", "score": 0.31952980160713196}, {"name": "Disgust", "score": 0.06777963787317276}, {"name": "Distress", "score": 0.2577476501464844}, {"name": "Doubt", "score": 0.1783640831708908}, {"name": "Ecstasy", "score": 0.06933297216892242}, {"name": "Embarrassment", "score": 0.14705969393253326}, {"name": "Empathic Pain", "score": 0.10050380229949951}, {"name": "Entrancement", "score": 0.11670396476984024}, {"name": "Envy", "score": 0.024697648361325264}, {"name": "Excitement", "score": 0.08262692391872406}, {"name": "Fear", "score": 0.08240976184606552}, {"name": "Guilt", "score": 0.11256643384695053}, {"name": "Horror", "score": 0.040447644889354706}, {"name": "Interest", "score": 0.17813125252723694}, {"name": "Joy", "score": 0.12107156962156296}, {"name": "Love", "score": 0.13156050443649292}, {"name": "Nostalgia", "score": 0.06985953450202942}, {"name": "Pain", "score": 0.2090304046869278}, {"name": "Pride", "score": 0.04846984148025513}, {"name": "Realization", "score": 0.174357071518898}, {"name": "Relief", "score": 0.18856211006641388}, {"name": "Romance", "score": 0.06623507291078568}, {"name": "Sadness", "score": 0.2402983456850052}, {"name": "Satisfaction", "score": 0.1986834853887558}, {"name": "Shame", "score": 0.12351273745298386}, {"name": "Surprise (negative)", "score": 0.051220424473285675}, {"name": "Surprise (positive)", "score": 0.04385426267981529}, {"name": "Sympathy", "score": 0.05570013076066971}, {"name": "Tiredness", "score": 0.5359597206115723}, {"name": "Triumph", "score": 0.03253304213285446}], "facs": null, "descriptions": null}]}]}}}], "errors": []}}, {"source": {"type": "file", "filename": "10.jpg", "content_type": "image/jpeg", "md5sum": "dae5210e0356742652f77f48e45623d8"}, "results": {"predictions": [{"file": "10.jpg", "file_type": "image", "models": {"face": {"metadata": null, "grouped_predictions": [{"id": "unknown", "predictions": [{"frame": 0, "time": 0.0, "prob": 0.9999929666519165, "box": {"x": 249.48788452148438, "y": 53.104637145996094, "w": 212.61480712890625, "h": 293.7243118286133}, "emotions": [{"name": "Admiration", "score": 0.09164732694625854}, {"name": "Adoration", "score": 0.07173773646354675}, {"name": "Aesthetic Appreciation", "score": 0.07340662181377411}, {"name": "Amusement", "score": 0.12395044416189194}, {"name": "Anger", "score": 0.06389150023460388}, {"name": "Anxiety", "score": 0.14179828763008118}, {"name": "Awe", "score": 0.06296326220035553}, {"name": "Awkwardness", "score": 0.19849944114685059}, {"name": "Boredom", "score": 0.6997379064559937}, {"name": "Calmness", "score": 0.7805618047714233}, {"name": "Concentration", "score": 0.6228752732276917}, {"name": "Confusion", "score": 0.2913786470890045}, {"name": "Contemplation", "score": 0.23546573519706726}, {"name": "Contempt", "score": 0.15678298473358154}, {"name": "Contentment", "score": 0.18254689872264862}, {"name": "Craving", "score": 0.04568997398018837}, {"name": "Desire", "score": 0.04600467532873154}, {"name": "Determination", "score": 0.1367921233177185}, {"name": "Disappointment", "score": 0.3128972351551056}, {"name": "Disgust", "score": 0.06134214252233505}, {"name": "Distress", "score": 0.1567153036594391}, {"name": "Doubt", "score": 0.272004634141922}, {"name": "Ecstasy", "score": 0.025275947526097298}, {"name": "Embarrassment", "score": 0.0908757671713829}, {"name": "Empathic Pain", "score": 0.07655099779367447}, {"name": "Entrancement", "score": 0.14510177075862885}, {"name": "Envy", "score": 0.045533470809459686}, {"name": "Excitement", "score": 0.04965686425566673}, {"name": "Fear", "score": 0.0625028982758522}, {"name": "Guilt", "score": 0.0878259688615799}, {"name": "Horror", "score": 0.024172557517886162}, {"name": "Interest", "score": 0.33973371982574463}, {"name": "Joy", "score": 0.09686382114887238}, {"name": "Love", "score": 0.09826841950416565}, {"name": "Nostalgia", "score": 0.07529588043689728}, {"name": "Pain", "score": 0.08304806798696518}, {"name": "Pride", "score": 0.06678924709558487}, {"name": "Realization", "score": 0.1349877417087555}, {"name": "Relief", "score": 0.07417193800210953}, {"name": "Romance", "score": 0.045139115303754807}, {"name": "Sadness", "score": 0.24673613905906677}, {"name": "Satisfaction", "score": 0.12825343012809753}, {"name": "Shame", "score": 0.08010751008987427}, {"name": "Surprise (negative)", "score": 0.037252653390169144}, {"name": "Surprise (positive)", "score": 0.03294604644179344}, {"name": "Sympathy", "score": 0.08353382349014282}, {"name": "Tiredness", "score": 0.35670217871665955}, {"name": "Triumph", "score": 0.022652167826890945}], "facs": null, "descriptions": null}]}]}}}], "errors": []}}, {"source": {"type": "file", "filename": "70.jpg", "content_type": "image/jpeg", "md5sum": "9a5c62325323bec7177de0758d72f834"}, "results": {"predictions": [{"file": "70.jpg", "file_type": "image", "models": {"face": {"metadata": null, "grouped_predictions": [{"id": "unknown", "predictions": [{"frame": 0, "time": 0.0, "prob": 0.9999939203262329, "box": {"x": 202.322265625, "y": -44.826412200927734, "w": 274.47723388671875, "h": 379.3170738220215}, "emotions": [{"name": "Admiration", "score": 0.1265702247619629}, {"name": "Adoration", "score": 0.0679549127817154}, {"name": "Aesthetic Appreciation", "score": 0.07585553824901581}, {"name": "Amusement", "score": 0.17089509963989258}, {"name": "Anger", "score": 0.04302472248673439}, {"name": "Anxiety", "score": 0.12290403991937637}, {"name": "Awe", "score": 0.33078116178512573}, {"name": "Awkwardness", "score": 0.21193090081214905}, {"name": "Boredom", "score": 0.3593750298023224}, {"name": "Calmness", "score": 0.3773350119590759}, {"name": "Concentration", "score": 0.47395601868629456}, {"name": "Confusion", "score": 0.4569369852542877}, {"name": "Contemplation", "score": 0.18210045993328094}, {"name": "Contempt", "score": 0.0994831994175911}, {"name": "Contentment", "score": 0.09246993809938431}, {"name": "Craving", "score": 0.07065480947494507}, {"name": "Desire", "score": 0.07797619700431824}, {"name": "Determination", "score": 0.1108287125825882}, {"name": "Disappointment", "score": 0.1772066056728363}, {"name": "Disgust", "score": 0.04477798193693161}, {"name": "Distress", "score": 0.1179441586136818}, {"name": "Doubt", "score": 0.3101740777492523}, {"name": "Ecstasy", "score": 0.04334256052970886}, {"name": "Embarrassment", "score": 0.08371546864509583}, {"name": "Empathic Pain", "score": 0.04399027302861214}, {"name": "Entrancement", "score": 0.1858810931444168}, {"name": "Envy", "score": 0.04096224904060364}, {"name": "Excitement", "score": 0.12140019983053207}, {"name": "Fear", "score": 0.12390400469303131}, {"name": "Guilt", "score": 0.05040658637881279}, {"name": "Horror", "score": 0.09481076896190643}, {"name": "Interest", "score": 0.41940611600875854}, {"name": "Joy", "score": 0.07988762855529785}, {"name": "Love", "score": 0.06831248104572296}, {"name": "Nostalgia", "score": 0.04667224362492561}, {"name": "Pain", "score": 0.03736656531691551}, {"name": "Pride", "score": 0.04380248859524727}, {"name": "Realization", "score": 0.25477445125579834}, {"name": "Relief", "score": 0.07685953378677368}, {"name": "Romance", "score": 0.04035826399922371}, {"name": "Sadness", "score": 0.0694284439086914}, {"name": "Satisfaction", "score": 0.09755454957485199}, {"name": "Shame", "score": 0.040746498852968216}, {"name": "Surprise (negative)", "score": 0.20522689819335938}, {"name": "Surprise (positive)", "score": 0.2984093725681305}, {"name": "Sympathy", "score": 0.05254095792770386}, {"name": "Tiredness", "score": 0.2099113166332245}, {"name": "Triumph", "score": 0.02921655774116516}], "facs": null, "descriptions": null}]}]}}}], "errors": []}}, {"source": {"type": "file", "filename": "90.jpg", "content_type": "image/jpeg", "md5sum": "59104dd52f83e456e11991f157f5b362"}, "results": {"predictions": [{"file": "90.jpg", "file_type": "image", "models": {"face": {"metadata": null, "grouped_predictions": [{"id": "unknown", "predictions": [{"frame": 0, "time": 0.0, "prob": 0.9999932050704956, "box": {"x": 214.73101806640625, "y": -57.358489990234375, "w": 269.32122802734375, "h": 390.23876953125}, "emotions": [{"name": "Admiration", "score": 0.14076384902000427}, {"name": "Adoration", "score": 0.06463263183832169}, {"name": "Aesthetic Appreciation", "score": 0.07417476177215576}, {"name": "Amusement", "score": 0.1584550142288208}, {"name": "Anger", "score": 0.03997618705034256}, {"name": "Anxiety", "score": 0.11466283351182938}, {"name": "Awe", "score": 0.48616328835487366}, {"name": "Awkwardness", "score": 0.19011615216732025}, {"name": "Boredom", "score": 0.26093220710754395}, {"name": "Calmness", "score": 0.28195881843566895}, {"name": "Concentration", "score": 0.4245399236679077}, {"name": "Confusion", "score": 0.45116186141967773}, {"name": "Contemplation", "score": 0.17782865464687347}, {"name": "Contempt", "score": 0.08795467019081116}, {"name": "Contentment", "score": 0.07148858904838562}, {"name": "Craving", "score": 0.06561488658189774}, {"name": "Desire", "score": 0.058657437562942505}, {"name": "Determination", "score": 0.10556316375732422}, {"name": "Disappointment", "score": 0.1492990106344223}, {"name": "Disgust", "score": 0.03731859475374222}, {"name": "Distress", "score": 0.10575941950082779}, {"name": "Doubt", "score": 0.31011369824409485}, {"name": "Ecstasy", "score": 0.04243997856974602}, {"name": "Embarrassment", "score": 0.07909029722213745}, {"name": "Empathic Pain", "score": 0.03669276461005211}, {"name": "Entrancement", "score": 0.1915345937013626}, {"name": "Envy", "score": 0.04060757905244827}, {"name": "Excitement", "score": 0.1290895640850067}, {"name": "Fear", "score": 0.14762727916240692}, {"name": "Guilt", "score": 0.044499825686216354}, {"name": "Horror", "score": 0.12975576519966125}, {"name": "Interest", "score": 0.4052315354347229}, {"name": "Joy", "score": 0.06115204468369484}, {"name": "Love", "score": 0.05396466702222824}, {"name": "Nostalgia", "score": 0.04343084990978241}, {"name": "Pain", "score": 0.027826888486742973}, {"name": "Pride", "score": 0.04146679490804672}, {"name": "Realization", "score": 0.30569466948509216}, {"name": "Relief", "score": 0.06946661323308945}, {"name": "Romance", "score": 0.032893575727939606}, {"name": "Sadness", "score": 0.04748621955513954}, {"name": "Satisfaction", "score": 0.07585110515356064}, {"name": "Shame", "score": 0.03338133171200752}, {"name": "Surprise (negative)", "score": 0.274034321308136}, {"name": "Surprise (positive)", "score": 0.44757160544395447}, {"name": "Sympathy", "score": 0.04516638442873955}, {"name": "Tiredness", "score": 0.1511850655078888}, {"name": "Triumph", "score": 0.030143331736326218}], "facs": null, "descriptions": null}]}]}}}], "errors": []}}, {"source": {"type": "file", "filename": "80.jpg", "content_type": "image/jpeg", "md5sum": "d895c520328cd0fa2b33b52ebf0ef8f9"}, "results": {"predictions": [{"file": "80.jpg", "file_type": "image", "models": {"face": {"metadata": null, "grouped_predictions": [{"id": "unknown", "predictions": [{"frame": 0, "time": 0.0, "prob": 0.9999912977218628, "box": {"x": 209.49278259277344, "y": -44.90477752685547, "w": 269.29283142089844, "h": 372.48094940185547}, "emotions": [{"name": "Admiration", "score": 0.13996736705303192}, {"name": "Adoration", "score": 0.06883344054222107}, {"name": "Aesthetic Appreciation", "score": 0.08171907812356949}, {"name": "Amusement", "score": 0.1250065267086029}, {"name": "Anger", "score": 0.04711678996682167}, {"name": "Anxiety", "score": 0.15361258387565613}, {"name": "Awe", "score": 0.3429703712463379}, {"name": "Awkwardness", "score": 0.20179150998592377}, {"name": "Boredom", "score": 0.32833126187324524}, {"name": "Calmness", "score": 0.3971395194530487}, {"name": "Concentration", "score": 0.5744223594665527}, {"name": "Confusion", "score": 0.5054090023040771}, {"name": "Contemplation", "score": 0.24665610492229462}, {"name": "Contempt", "score": 0.10862577706575394}, {"name": "Contentment", "score": 0.08305951207876205}, {"name": "Craving", "score": 0.07034987956285477}, {"name": "Desire", "score": 0.0573553703725338}, {"name": "Determination", "score": 0.13102473318576813}, {"name": "Disappointment", "score": 0.19364240765571594}, {"name": "Disgust", "score": 0.043705906718969345}, {"name": "Distress", "score": 0.1384640634059906}, {"name": "Doubt", "score": 0.37087661027908325}, {"name": "Ecstasy", "score": 0.03121821954846382}, {"name": "Embarrassment", "score": 0.08609305322170258}, {"name": "Empathic Pain", "score": 0.05135985463857651}, {"name": "Entrancement", "score": 0.21286703646183014}, {"name": "Envy", "score": 0.04808984696865082}, {"name": "Excitement", "score": 0.08566322922706604}, {"name": "Fear", "score": 0.17156937718391418}, {"name": "Guilt", "score": 0.06478600949048996}, {"name": "Horror", "score": 0.1058831438422203}, {"name": "Interest", "score": 0.42383521795272827}, {"name": "Joy", "score": 0.053813692182302475}, {"name": "Love", "score": 0.057895541191101074}, {"name": "Nostalgia", "score": 0.05678535997867584}, {"name": "Pain", "score": 0.04113695025444031}, {"name": "Pride", "score": 0.043351493775844574}, {"name": "Realization", "score": 0.2814081311225891}, {"name": "Relief", "score": 0.06441083550453186}, {"name": "Romance", "score": 0.037541355937719345}, {"name": "Sadness", "score": 0.09377855807542801}, {"name": "Satisfaction", "score": 0.07190580666065216}, {"name": "Shame", "score": 0.044916801154613495}, {"name": "Surprise (negative)", "score": 0.19880174100399017}, {"name": "Surprise (positive)", "score": 0.25409257411956787}, {"name": "Sympathy", "score": 0.05609004944562912}, {"name": "Tiredness", "score": 0.17284443974494934}, {"name": "Triumph", "score": 0.024120470508933067}], "facs": null, "descriptions": null}]}]}}}], "errors": []}}, {"source": {"type": "file", "filename": "50.jpg", "content_type": "image/jpeg", "md5sum": "a33f2c57c21ee768c217350c3a07c838"}, "results": {"predictions": [{"file": "50.jpg", "file_type": "image", "models": {"face": {"metadata": null, "grouped_predictions": [{"id": "unknown", "predictions": [{"frame": 0, "time": 0.0, "prob": 0.9999955892562866, "box": {"x": 217.29986572265625, "y": -38.83637619018555, "w": 282.11669921875, "h": 388.6762809753418}, "emotions": [{"name": "Admiration", "score": 0.11332441866397858}, {"name": "Adoration", "score": 0.07048498094081879}, {"name": "Aesthetic Appreciation", "score": 0.07769675552845001}, {"name": "Amusement", "score": 0.15724380314350128}, {"name": "Anger", "score": 0.04719240218400955}, {"name": "Anxiety", "score": 0.13212436437606812}, {"name": "Awe", "score": 0.19286563992500305}, {"name": "Awkwardness", "score": 0.21179291605949402}, {"name": "Boredom", "score": 0.44507041573524475}, {"name": "Calmness", "score": 0.48025453090667725}, {"name": "Concentration", "score": 0.5447025895118713}, {"name": "Confusion", "score": 0.43571919202804565}, {"name": "Contemplation", "score": 0.2088700532913208}, {"name": "Contempt", "score": 0.11714719235897064}, {"name": "Contentment", "score": 0.11266793310642242}, {"name": "Craving", "score": 0.07235483825206757}, {"name": "Desire", "score": 0.09323430806398392}, {"name": "Determination", "score": 0.12247760593891144}, {"name": "Disappointment", "score": 0.21159988641738892}, {"name": "Disgust", "score": 0.05210964381694794}, {"name": "Distress", "score": 0.1333383321762085}, {"name": "Doubt", "score": 0.31320255994796753}, {"name": "Ecstasy", "score": 0.039742179214954376}, {"name": "Embarrassment", "score": 0.08740398287773132}, {"name": "Empathic Pain", "score": 0.0522228479385376}, {"name": "Entrancement", "score": 0.18079224228858948}, {"name": "Envy", "score": 0.041792646050453186}, {"name": "Excitement", "score": 0.09426935762166977}, {"name": "Fear", "score": 0.09398376941680908}, {"name": "Guilt", "score": 0.06176156923174858}, {"name": "Horror", "score": 0.057549890130758286}, {"name": "Interest", "score": 0.4094325304031372}, {"name": "Joy", "score": 0.08163205534219742}, {"name": "Love", "score": 0.082308828830719}, {"name": "Nostalgia", "score": 0.053054407238960266}, {"name": "Pain", "score": 0.04925859346985817}, {"name": "Pride", "score": 0.04748435318470001}, {"name": "Realization", "score": 0.21857701241970062}, {"name": "Relief", "score": 0.08692294359207153}, {"name": "Romance", "score": 0.049893610179424286}, {"name": "Sadness", "score": 0.09965503960847855}, {"name": "Satisfaction", "score": 0.11267706006765366}, {"name": "Shame", "score": 0.05189982056617737}, {"name": "Surprise (negative)", "score": 0.11913179606199265}, {"name": "Surprise (positive)", "score": 0.15370169281959534}, {"name": "Sympathy", "score": 0.05823548883199692}, {"name": "Tiredness", "score": 0.26843494176864624}, {"name": "Triumph", "score": 0.026986896991729736}], "facs": null, "descriptions": null}]}]}}}], "errors": []}}, {"source": {"type": "file", "filename": "60.jpg", "content_type": "image/jpeg", "md5sum": "174a6af87beaa36db2b00ebabe2d8359"}, "results": {"predictions": [{"file": "60.jpg", "file_type": "image", "models": {"face": {"metadata": null, "grouped_predictions": [{"id": "unknown", "predictions": [{"frame": 0, "time": 0.0, "prob": 0.9999978542327881, "box": {"x": 222.19558715820312, "y": -3.0167007446289062, "w": 260.1471252441406, "h": 356.42655181884766}, "emotions": [{"name": "Admiration", "score": 0.15438033640384674}, {"name": "Adoration", "score": 0.12343236804008484}, {"name": "Aesthetic Appreciation", "score": 0.09417279064655304}, {"name": "Amusement", "score": 0.29648852348327637}, {"name": "Anger", "score": 0.05517423897981644}, {"name": "Anxiety", "score": 0.1258644312620163}, {"name": "Awe", "score": 0.11796697229146957}, {"name": "Awkwardness", "score": 0.2549571990966797}, {"name": "Boredom", "score": 0.34380120038986206}, {"name": "Calmness", "score": 0.4995265603065491}, {"name": "Concentration", "score": 0.4622710049152374}, {"name": "Confusion", "score": 0.3390197455883026}, {"name": "Contemplation", "score": 0.18039241433143616}, {"name": "Contempt", "score": 0.142738938331604}, {"name": "Contentment", "score": 0.19791501760482788}, {"name": "Craving", "score": 0.0787033885717392}, {"name": "Desire", "score": 0.10768957436084747}, {"name": "Determination", "score": 0.12374274432659149}, {"name": "Disappointment", "score": 0.18102702498435974}, {"name": "Disgust", "score": 0.06930997222661972}, {"name": "Distress", "score": 0.12175669521093369}, {"name": "Doubt", "score": 0.2576165199279785}, {"name": "Ecstasy", "score": 0.05814112350344658}, {"name": "Embarrassment", "score": 0.08981115370988846}, {"name": "Empathic Pain", "score": 0.05370247736573219}, {"name": "Entrancement", "score": 0.15282472968101501}, {"name": "Envy", "score": 0.04821676388382912}, {"name": "Excitement", "score": 0.161714568734169}, {"name": "Fear", "score": 0.08584298193454742}, {"name": "Guilt", "score": 0.056046828627586365}, {"name": "Horror", "score": 0.04491716995835304}, {"name": "Interest", "score": 0.4903353750705719}, {"name": "Joy", "score": 0.2350904792547226}, {"name": "Love", "score": 0.1787378042936325}, {"name": "Nostalgia", "score": 0.06405998021364212}, {"name": "Pain", "score": 0.05696826055645943}, {"name": "Pride", "score": 0.080935537815094}, {"name": "Realization", "score": 0.1546754240989685}, {"name": "Relief", "score": 0.08416382968425751}, {"name": "Romance", "score": 0.0769382119178772}, {"name": "Sadness", "score": 0.1004609614610672}, {"name": "Satisfaction", "score": 0.20652137696743011}, {"name": "Shame", "score": 0.051525574177503586}, {"name": "Surprise (negative)", "score": 0.0685107409954071}, {"name": "Surprise (positive)", "score": 0.08126995712518692}, {"name": "Sympathy", "score": 0.07024990022182465}, {"name": "Tiredness", "score": 0.16706271469593048}, {"name": "Triumph", "score": 0.04497259855270386}], "facs": null, "descriptions": null}]}]}}}], "errors": []}}, {"source": {"type": "file", "filename": "40.jpg", "content_type": "image/jpeg", "md5sum": "7e55e29435b25f7237087c91ab2d29a1"}, "results": {"predictions": [{"file": "40.jpg", "file_type": "image", "models": {"face": {"metadata": null, "grouped_predictions": [{"id": "unknown", "predictions": [{"frame": 0, "time": 0.0, "prob": 0.9999996423721313, "box": {"x": 215.7380828857422, "y": 8.660415649414062, "w": 262.27833557128906, "h": 349.17283630371094}, "emotions": [{"name": "Admiration", "score": 0.11255371570587158}, {"name": "Adoration", "score": 0.08855274319648743}, {"name": "Aesthetic Appreciation", "score": 0.08496421575546265}, {"name": "Amusement", "score": 0.16701726615428925}, {"name": "Anger", "score": 0.058541979640722275}, {"name": "Anxiety", "score": 0.12885642051696777}, {"name": "Awe", "score": 0.0797673761844635}, {"name": "Awkwardness", "score": 0.2174120843410492}, {"name": "Boredom", "score": 0.5464871525764465}, {"name": "Calmness", "score": 0.7268062829971313}, {"name": "Concentration", "score": 0.5888830423355103}, {"name": "Confusion", "score": 0.3353523910045624}, {"name": "Contemplation", "score": 0.2115790694952011}, {"name": "Contempt", "score": 0.15885356068611145}, {"name": "Contentment", "score": 0.19518987834453583}, {"name": "Craving", "score": 0.06019645184278488}, {"name": "Desire", "score": 0.0795072615146637}, {"name": "Determination", "score": 0.13463334739208221}, {"name": "Disappointment", "score": 0.24522727727890015}, {"name": "Disgust", "score": 0.06677711755037308}, {"name": "Distress", "score": 0.1365075409412384}, {"name": "Doubt", "score": 0.26924943923950195}, {"name": "Ecstasy", "score": 0.035393767058849335}, {"name": "Embarrassment", "score": 0.08224871009588242}, {"name": "Empathic Pain", "score": 0.06410929560661316}, {"name": "Entrancement", "score": 0.16013839840888977}, {"name": "Envy", "score": 0.04656319320201874}, {"name": "Excitement", "score": 0.0761488527059555}, {"name": "Fear", "score": 0.06474491208791733}, {"name": "Guilt", "score": 0.06833741068840027}, {"name": "Horror", "score": 0.02800832688808441}, {"name": "Interest", "score": 0.40526360273361206}, {"name": "Joy", "score": 0.13425807654857635}, {"name": "Love", "score": 0.12630195915699005}, {"name": "Nostalgia", "score": 0.07070182263851166}, {"name": "Pain", "score": 0.0691901296377182}, {"name": "Pride", "score": 0.0697718933224678}, {"name": "Realization", "score": 0.14368480443954468}, {"name": "Relief", "score": 0.0877489447593689}, {"name": "Romance", "score": 0.0602441132068634}, {"name": "Sadness", "score": 0.16168580949306488}, {"name": "Satisfaction", "score": 0.16343721747398376}, {"name": "Shame", "score": 0.06183892861008644}, {"name": "Surprise (negative)", "score": 0.04685424268245697}, {"name": "Surprise (positive)", "score": 0.04516110196709633}, {"name": "Sympathy", "score": 0.07579097151756287}, {"name": "Tiredness", "score": 0.29416853189468384}, {"name": "Triumph", "score": 0.028617728501558304}], "facs": null, "descriptions": null}]}]}}}], "errors": []}}]